{"v":"4.8.0","meta":{"g":"LottieFiles AE 3.5.5","a":"","k":"","d":"","tc":""},"fr":60,"ip":0,"op":60,"w":512,"h":512,"nm":"4","ddd":0,"assets":[],"layers":[{"ddd":0,"ind":1,"ty":4,"nm":"Layer 2 Outlines 2","sr":1,"ks":{"o":{"a":0,"k":100,"ix":11},"r":{"a":1,"k":[{"i":{"x":[0.667],"y":[1]},"o":{"x":[0.333],"y":[0]},"t":0,"s":[0]},{"t":60,"s":[180]}],"ix":10},"p":{"a":0,"k":[253.005,260.463,0],"ix":2},"a":{"a":0,"k":[253.005,260.463,0],"ix":1},"s":{"a":0,"k":[-100,-100,100],"ix":6}},"ao":0,"shapes":[{"ty":"gr","it":[{"ind":0,"ty":"sh","ix":1,"ks":{"a":0,"k":{"i":[[0,-34.007],[-34.098,0],[0,34.005],[34.103,0]],"o":[[0,33.996],[34.098,0],[0,-34.005],[-34.102,0]],"v":[[-61.742,-0.003],[-0.001,61.57],[61.743,-0.003],[-0.001,-61.57]],"c":true},"ix":2},"nm":"Path 1","mn":"ADBE Vector Shape - Group","hd":false},{"ind":1,"ty":"sh","ix":2,"ks":{"a":0,"k":{"i":[[0,0],[0,0],[0,0],[0,0]],"o":[[0,0],[0,0],[0,0],[0,0]],"v":[[-20.878,-0.003],[-0.001,-20.825],[20.879,-0.003],[-0.001,20.817]],"c":true},"ix":2},"nm":"Path 2","mn":"ADBE Vector Shape - Group","hd":false},{"ty":"mm","mm":1,"nm":"Merge Paths 1","mn":"ADBE Vector Filter - Merge","hd":false},{"ty":"gf","o":{"a":0,"k":100,"ix":10},"r":1,"bm":0,"g":{"p":3,"k":{"a":0,"k":[0,0.984,1,0.278,0.5,0.992,0.843,0.176,1,1,0.686,0.075],"ix":9}},"s":{"a":0,"k":[36,47.5],"ix":5},"e":{"a":0,"k":[-37,-49],"ix":6},"t":2,"h":{"a":0,"k":0,"ix":7},"a":{"a":0,"k":0,"ix":8},"nm":"Gradient Fill 1","mn":"ADBE Vector Graphic - G-Fill","hd":false},{"ty":"tr","p":{"a":0,"k":[385.31,378.476],"ix":2},"a":{"a":0,"k":[0,0],"ix":1},"s":{"a":0,"k":[100,100],"ix":3},"r":{"a":0,"k":0,"ix":6},"o":{"a":0,"k":100,"ix":7},"sk":{"a":0,"k":0,"ix":4},"sa":{"a":0,"k":0,"ix":5},"nm":"Transform"}],"nm":"Group 1","np":4,"cix":2,"bm":0,"ix":1,"mn":"ADBE Vector Group","hd":false}],"ip":0,"op":180,"st":0,"bm":0},{"ddd":0,"ind":2,"ty":4,"nm":"Layer 2 Outlines","sr":1,"ks":{"o":{"a":0,"k":100,"ix":11},"r":{"a":1,"k":[{"i":{"x":[0.667],"y":[1]},"o":{"x":[0.333],"y":[0]},"t":0,"s":[0]},{"t":60,"s":[180]}],"ix":10},"p":{"a":0,"k":[253.005,260.463,0],"ix":2},"a":{"a":0,"k":[253.005,260.463,0],"ix":1},"s":{"a":0,"k":[100,100,100],"ix":6}},"ao":0,"shapes":[{"ty":"gr","it":[{"ind":0,"ty":"sh","ix":1,"ks":{"a":0,"k":{"i":[[0,-34.007],[-34.098,0],[0,34.005],[34.103,0]],"o":[[0,33.996],[34.098,0],[0,-34.005],[-34.102,0]],"v":[[-61.742,-0.003],[-0.001,61.57],[61.743,-0.003],[-0.001,-61.57]],"c":true},"ix":2},"nm":"Path 1","mn":"ADBE Vector Shape - Group","hd":false},{"ind":1,"ty":"sh","ix":2,"ks":{"a":0,"k":{"i":[[0,0],[0,0],[0,0],[0,0]],"o":[[0,0],[0,0],[0,0],[0,0]],"v":[[-20.878,-0.003],[-0.001,-20.825],[20.879,-0.003],[-0.001,20.817]],"c":true},"ix":2},"nm":"Path 2","mn":"ADBE Vector Shape - Group","hd":false},{"ty":"mm","mm":1,"nm":"Merge Paths 1","mn":"ADBE Vector Filter - Merge","hd":false},{"ty":"gf","o":{"a":0,"k":100,"ix":10},"r":1,"bm":0,"g":{"p":3,"k":{"a":0,"k":[0,0.984,1,0.278,0.5,0.992,0.843,0.176,1,1,0.686,0.075],"ix":9}},"s":{"a":0,"k":[36,47.5],"ix":5},"e":{"a":0,"k":[-37,-49],"ix":6},"t":2,"h":{"a":0,"k":0,"ix":7},"a":{"a":0,"k":0,"ix":8},"nm":"Gradient Fill 1","mn":"ADBE Vector Graphic - G-Fill","hd":false},{"ty":"tr","p":{"a":0,"k":[385.31,378.476],"ix":2},"a":{"a":0,"k":[0,0],"ix":1},"s":{"a":0,"k":[100,100],"ix":3},"r":{"a":0,"k":0,"ix":6},"o":{"a":0,"k":100,"ix":7},"sk":{"a":0,"k":0,"ix":4},"sa":{"a":0,"k":0,"ix":5},"nm":"Transform"}],"nm":"Group 1","np":4,"cix":2,"bm":0,"ix":1,"mn":"ADBE Vector Group","hd":false}],"ip":0,"op":180,"st":0,"bm":0},{"ddd":0,"ind":3,"ty":4,"nm":"Layer 5 Outlines","sr":1,"ks":{"o":{"a":0,"k":100,"ix":11},"r":{"a":1,"k":[{"i":{"x":[0.667],"y":[1]},"o":{"x":[0.333],"y":[0]},"t":0,"s":[0]},{"t":60,"s":[180]}],"ix":10},"p":{"a":0,"k":[253.008,260.454,0],"ix":2},"a":{"a":0,"k":[253.008,260.454,0],"ix":1},"s":{"a":0,"k":[100,100,100],"ix":6}},"ao":0,"shapes":[{"ty":"gr","it":[{"ind":0,"ty":"sh","ix":1,"ks":{"a":0,"k":{"i":[[0,0],[8.72,20.656],[16.03,16.029],[20.855,8.832],[23.467,-0.046],[0,0],[-1.746,-93.547],[0,0],[0,0],[0,0]],"o":[[-0.367,-22.427],[-8.81,-20.911],[-15.985,-16.075],[-21.61,-9.172],[0,0],[93.714,0],[0,0],[0,0],[0,0],[0,0]],"v":[[83.041,76.697],[69.282,11.466],[31.669,-44.471],[-24.119,-82.187],[-92.433,-96.017],[-92.433,-92.429],[79.462,76.697],[70.127,76.697],[81.281,96.063],[92.433,76.697]],"c":true},"ix":2},"nm":"Path 1","mn":"ADBE Vector Shape - Group","hd":false},{"ty":"fl","c":{"a":0,"k":[0.136999990426,0.46699999641,0.987999949736,1],"ix":4},"o":{"a":0,"k":100,"ix":5},"r":1,"bm":0,"nm":"Fill 1","mn":"ADBE Vector Graphic - Fill","hd":false},{"ty":"tr","p":{"a":0,"k":[345.441,180.488],"ix":2},"a":{"a":0,"k":[0,0],"ix":1},"s":{"a":0,"k":[100,100],"ix":3},"r":{"a":0,"k":0,"ix":6},"o":{"a":0,"k":100,"ix":7},"sk":{"a":0,"k":0,"ix":4},"sa":{"a":0,"k":0,"ix":5},"nm":"Transform"}],"nm":"Group 1","np":2,"cix":2,"bm":0,"ix":1,"mn":"ADBE Vector Group","hd":false},{"ty":"gr","it":[{"ind":0,"ty":"sh","ix":1,"ks":{"a":0,"k":{"i":[[1.745,93.556],[0,0],[0,0],[0,0],[0,0],[-8.721,-20.656],[-16.028,-16.032],[-20.854,-8.832],[-23.468,0.047],[0,0]],"o":[[0,0],[0,0],[0,0],[0,0],[0.368,22.428],[8.81,20.911],[15.987,16.073],[21.613,9.172],[0,0],[-93.711,-0.011]],"v":[[-79.458,-76.709],[-70.129,-76.709],[-81.283,-96.064],[-92.435,-76.698],[-83.041,-76.698],[-69.281,-11.467],[-31.669,44.473],[24.118,82.186],[92.435,96.017],[92.435,92.428]],"c":true},"ix":2},"nm":"Path 1","mn":"ADBE Vector Shape - Group","hd":false},{"ty":"fl","c":{"a":0,"k":[0.136999990426,0.46699999641,0.987999949736,1],"ix":4},"o":{"a":0,"k":100,"ix":5},"r":1,"bm":0,"nm":"Fill 1","mn":"ADBE Vector Graphic - Fill","hd":false},{"ty":"tr","p":{"a":0,"k":[160.571,340.439],"ix":2},"a":{"a":0,"k":[0,0],"ix":1},"s":{"a":0,"k":[100,100],"ix":3},"r":{"a":0,"k":0,"ix":6},"o":{"a":0,"k":100,"ix":7},"sk":{"a":0,"k":0,"ix":4},"sa":{"a":0,"k":0,"ix":5},"nm":"Transform"}],"nm":"Group 2","np":2,"cix":2,"bm":0,"ix":2,"mn":"ADBE Vector Group","hd":false}],"ip":0,"op":180,"st":0,"bm":0},{"ddd":0,"ind":4,"ty":4,"nm":"Layer 4 Outlines","sr":1,"ks":{"o":{"a":0,"k":100,"ix":11},"r":{"a":0,"k":0,"ix":10},"p":{"a":0,"k":[253.005,260.463,0],"ix":2},"a":{"a":0,"k":[253.005,260.463,0],"ix":1},"s":{"a":0,"k":[100,100,100],"ix":6}},"ao":0,"shapes":[{"ty":"gr","it":[{"ind":0,"ty":"sh","ix":1,"ks":{"a":0,"k":{"i":[[0,0],[-5.88,-21.565],[-19.836,0.236],[0,0]],"o":[[0.304,26.604],[17.949,-3.618],[0,0],[0,0]],"v":[[-33.368,-36.525],[-23.709,36.525],[33.369,30.621],[33.369,-36.525]],"c":true},"ix":2},"nm":"Path 2","mn":"ADBE Vector Shape - Group","hd":false},{"ty":"gf","o":{"a":0,"k":100,"ix":10},"r":1,"bm":0,"g":{"p":3,"k":{"a":0,"k":[0,0.631,0.776,1,0.5,0.386,0.624,0.994,1,0.141,0.471,0.988],"ix":9}},"s":{"a":0,"k":[38,111.875],"ix":5},"e":{"a":0,"k":[37.5,-192.875],"ix":6},"t":1,"nm":"Gradient Fill 1","mn":"ADBE Vector Graphic - G-Fill","hd":false},{"ty":"tr","p":{"a":0,"k":[215.66,300.923],"ix":2},"a":{"a":0,"k":[0,0],"ix":1},"s":{"a":0,"k":[100,100],"ix":3},"r":{"a":0,"k":0,"ix":6},"o":{"a":0,"k":100,"ix":7},"sk":{"a":0,"k":0,"ix":4},"sa":{"a":0,"k":0,"ix":5},"nm":"Transform"}],"nm":"Group 1","np":2,"cix":2,"bm":0,"ix":1,"mn":"ADBE Vector Group","hd":false},{"ty":"gr","it":[{"ind":0,"ty":"sh","ix":1,"ks":{"a":0,"k":{"i":[[17.249,-3.436],[-22.901,-2.753],[0,0]],"o":[[12.006,38.772],[0,0],[-19.121,0.245]],"v":[[-27.471,-31.034],[27.471,36.622],[27.471,-36.622]],"c":true},"ix":2},"nm":"Path 1","mn":"ADBE Vector Shape - Group","hd":false},{"ty":"gf","o":{"a":0,"k":100,"ix":10},"r":1,"bm":0,"g":{"p":3,"k":{"a":0,"k":[0,0.631,0.776,1,0.5,0.386,0.624,0.994,1,0.141,0.471,0.988],"ix":9}},"s":{"a":0,"k":[30,37.875],"ix":5},"e":{"a":0,"k":[30.5,-267.875],"ix":6},"t":1,"nm":"Gradient Fill 1","mn":"ADBE Vector Graphic - G-Fill","hd":false},{"ty":"tr","p":{"a":0,"k":[221.561,376.039],"ix":2},"a":{"a":0,"k":[0,0],"ix":1},"s":{"a":0,"k":[100,100],"ix":3},"r":{"a":0,"k":0,"ix":6},"o":{"a":0,"k":100,"ix":7},"sk":{"a":0,"k":0,"ix":4},"sa":{"a":0,"k":0,"ix":5},"nm":"Transform"}],"nm":"Group 2","np":2,"cix":2,"bm":0,"ix":2,"mn":"ADBE Vector Group","hd":false},{"ty":"gr","it":[{"ind":0,"ty":"sh","ix":1,"ks":{"a":0,"k":{"i":[[0,0],[-21.287,-26.184],[-18.363,4.279],[0.309,27.269]],"o":[[0.864,33.769],[14.01,-7.482],[-5.961,-22.059],[0,0]],"v":[[-41.587,-46.24],[-7.417,46.24],[41.587,28.471],[31.875,-46.24]],"c":true},"ix":2},"nm":"Path 1","mn":"ADBE Vector Shape - Group","hd":false},{"ty":"gf","o":{"a":0,"k":100,"ix":10},"r":1,"bm":0,"g":{"p":3,"k":{"a":0,"k":[0,0.631,0.776,1,0.5,0.386,0.624,0.994,1,0.141,0.471,0.988],"ix":9}},"s":{"a":0,"k":[109,98.875],"ix":5},"e":{"a":0,"k":[109.5,-202.875],"ix":6},"t":1,"nm":"Gradient Fill 1","mn":"ADBE Vector Graphic - G-Fill","hd":false},{"ty":"tr","p":{"a":0,"k":[142.544,310.638],"ix":2},"a":{"a":0,"k":[0,0],"ix":1},"s":{"a":0,"k":[100,100],"ix":3},"r":{"a":0,"k":0,"ix":6},"o":{"a":0,"k":100,"ix":7},"sk":{"a":0,"k":0,"ix":4},"sa":{"a":0,"k":0,"ix":5},"nm":"Transform"}],"nm":"Group 3","np":2,"cix":2,"bm":0,"ix":3,"mn":"ADBE Vector Group","hd":false},{"ty":"gr","it":[{"ind":0,"ty":"sh","ix":1,"ks":{"a":0,"k":{"i":[[0.736,-0.15],[1.951,-0.488],[2.916,-0.922],[2.265,-0.828],[2.767,-1.207],[0.551,-0.253],[4.039,-2.285],[0.567,-0.324],[3.764,-2.704],[0.094,-0.062],[1.342,-1.031],[2.336,-2.039],[1.425,-1.335],[2.129,-2.255],[0.71,-0.788],[-17.17,-3.949],[-15.914,12.321]],"o":[[-1.975,0.411],[-2.978,0.74],[-2.288,0.717],[-2.839,1.047],[-0.543,0.244],[-4.249,1.909],[-0.575,0.323],[-3.978,2.325],[-0.093,0.063],[-1.384,0.988],[-2.446,1.884],[-1.471,1.285],[-2.236,2.112],[-0.723,0.762],[13.179,6.819],[8.873,-28.897],[-0.747,0.141]],"v":[[39.808,-31.447],[33.95,-29.98],[25.074,-27.591],[18.282,-25.162],[9.831,-21.915],[8.187,-21.197],[-4.226,-14.875],[-5.933,-13.906],[-17.545,-6.362],[-17.82,-6.165],[-21.846,-3.043],[-29.048,2.789],[-33.358,6.756],[-39.906,13.307],[-42.045,15.631],[3.996,31.8],[42.045,-31.8]],"c":true},"ix":2},"nm":"Path 1","mn":"ADBE Vector Shape - Group","hd":false},{"ty":"gf","o":{"a":0,"k":100,"ix":10},"r":1,"bm":0,"g":{"p":3,"k":{"a":0,"k":[0,0.631,0.776,1,0.5,0.386,0.624,0.994,1,0.141,0.471,0.988],"ix":9}},"s":{"a":0,"k":[70,267.875],"ix":5},"e":{"a":0,"k":[70.5,-33.875],"ix":6},"t":1,"nm":"Gradient Fill 1","mn":"ADBE Vector Graphic - G-Fill","hd":false},{"ty":"tr","p":{"a":0,"k":[182.378,142.457],"ix":2},"a":{"a":0,"k":[0,0],"ix":1},"s":{"a":0,"k":[100,100],"ix":3},"r":{"a":0,"k":0,"ix":6},"o":{"a":0,"k":100,"ix":7},"sk":{"a":0,"k":0,"ix":4},"sa":{"a":0,"k":0,"ix":5},"nm":"Transform"}],"nm":"Group 4","np":2,"cix":2,"bm":0,"ix":4,"mn":"ADBE Vector Group","hd":false},{"ty":"gr","it":[{"ind":0,"ty":"sh","ix":1,"ks":{"a":0,"k":{"i":[[0.88,-33.737],[0,0],[-5.945,22.041],[13.973,7.467]],"o":[[0,0],[0.315,-27.253],[-18.389,-4.261],[-21.269,26.157]],"v":[[-41.581,46.193],[31.87,46.193],[41.581,-28.462],[-7.417,-46.193]],"c":true},"ix":2},"nm":"Path 2","mn":"ADBE Vector Shape - Group","hd":false},{"ty":"gf","o":{"a":0,"k":100,"ix":10},"r":1,"bm":0,"g":{"p":3,"k":{"a":0,"k":[0,0.631,0.776,1,0.5,0.386,0.624,0.994,1,0.141,0.471,0.988],"ix":9}},"s":{"a":0,"k":[110,200.875],"ix":5},"e":{"a":0,"k":[110.5,-99.875],"ix":6},"t":1,"nm":"Gradient Fill 1","mn":"ADBE Vector Graphic - G-Fill","hd":false},{"ty":"tr","p":{"a":0,"k":[142.548,210.322],"ix":2},"a":{"a":0,"k":[0,0],"ix":1},"s":{"a":0,"k":[100,100],"ix":3},"r":{"a":0,"k":0,"ix":6},"o":{"a":0,"k":100,"ix":7},"sk":{"a":0,"k":0,"ix":4},"sa":{"a":0,"k":0,"ix":5},"nm":"Transform"}],"nm":"Group 5","np":2,"cix":2,"bm":0,"ix":5,"mn":"ADBE Vector Group","hd":false},{"ty":"gr","it":[{"ind":0,"ty":"sh","ix":1,"ks":{"a":0,"k":{"i":[[0.313,-26.59],[0,0],[0,0],[17.937,3.595]],"o":[[0,0],[0,0],[-19.859,-0.245],[-5.882,21.553]],"v":[[-33.373,36.508],[33.374,36.508],[33.374,-30.634],[-23.704,-36.508]],"c":true},"ix":2},"nm":"Path 2","mn":"ADBE Vector Shape - Group","hd":false},{"ty":"gf","o":{"a":0,"k":100,"ix":10},"r":1,"bm":0,"g":{"p":3,"k":{"a":0,"k":[0,0.631,0.776,1,0.5,0.386,0.624,0.994,1,0.141,0.471,0.988],"ix":9}},"s":{"a":0,"k":[37.375,192.625],"ix":5},"e":{"a":0,"k":[37.25,-111.75],"ix":6},"t":1,"nm":"Gradient Fill 1","mn":"ADBE Vector Graphic - G-Fill","hd":false},{"ty":"tr","p":{"a":0,"k":[215.665,220.009],"ix":2},"a":{"a":0,"k":[0,0],"ix":1},"s":{"a":0,"k":[100,100],"ix":3},"r":{"a":0,"k":0,"ix":6},"o":{"a":0,"k":100,"ix":7},"sk":{"a":0,"k":0,"ix":4},"sa":{"a":0,"k":0,"ix":5},"nm":"Transform"}],"nm":"Group 6","np":2,"cix":2,"bm":0,"ix":6,"mn":"ADBE Vector Group","hd":false},{"ty":"gr","it":[{"ind":0,"ty":"sh","ix":1,"ks":{"a":0,"k":{"i":[[15.904,-12.321],[-0.581,0.117],[-0.709,0.161],[-4.196,1.3],[-0.942,0.315],[-3.854,1.648],[-1.069,0.489],[-3.57,1.996],[-1.069,0.63],[-3.341,2.348],[-0.981,0.732],[-3.16,2.784],[-0.793,0.717],[-3.02,3.273],[-0.243,0.268],[17.17,3.975]],"o":[[0.573,-0.117],[0.708,-0.143],[4.314,-0.937],[0.943,-0.298],[3.978,-1.325],[1.068,-0.448],[3.704,-1.687],[1.085,-0.608],[3.508,-2.067],[0.997,-0.702],[3.357,-2.484],[0.81,-0.702],[3.253,-2.991],[0.252,-0.279],[-13.206,-6.859],[-8.88,28.884]],"v":[[-42.07,31.785],[-40.326,31.503],[-38.178,31.083],[-25.43,27.671],[-22.593,26.789],[-10.853,22.286],[-7.64,20.9],[3.266,15.35],[6.511,13.513],[16.772,6.867],[19.742,4.731],[29.516,-3.169],[31.914,-5.305],[41.324,-14.7],[42.07,-15.53],[-4.023,-31.786]],"c":true},"ix":2},"nm":"Path 2","mn":"ADBE Vector Shape - Group","hd":false},{"ty":"gf","o":{"a":0,"k":100,"ix":10},"r":1,"bm":0,"g":{"p":3,"k":{"a":0,"k":[0,0.631,0.776,1,0.5,0.386,0.624,0.994,1,0.141,0.471,0.988],"ix":9}},"s":{"a":0,"k":[-72,30.875],"ix":5},"e":{"a":0,"k":[-70.5,-269.875],"ix":6},"t":1,"nm":"Gradient Fill 1","mn":"ADBE Vector Graphic - G-Fill","hd":false},{"ty":"tr","p":{"a":0,"k":[323.678,378.475],"ix":2},"a":{"a":0,"k":[0,0],"ix":1},"s":{"a":0,"k":[100,100],"ix":3},"r":{"a":0,"k":0,"ix":6},"o":{"a":0,"k":100,"ix":7},"sk":{"a":0,"k":0,"ix":4},"sa":{"a":0,"k":0,"ix":5},"nm":"Transform"}],"nm":"Group 7","np":2,"cix":2,"bm":0,"ix":7,"mn":"ADBE Vector Group","hd":false},{"ty":"gr","it":[{"ind":0,"ty":"sh","ix":1,"ks":{"a":0,"k":{"i":[[13.215,-6.857],[-0.251,-0.276],[-3.262,-2.974],[-0.81,-0.702],[-3.361,-2.481],[-0.998,-0.702],[-3.508,-2.064],[-1.085,-0.605],[-3.702,-1.686],[-1.069,-0.456],[-3.976,-1.325],[-0.944,-0.299],[-4.32,-0.947],[-0.708,-0.143],[-0.573,-0.117],[8.878,28.879]],"o":[[0.244,0.27],[3.011,3.289],[0.794,0.716],[3.153,2.784],[0.985,0.735],[3.341,2.35],[1.069,0.634],[3.578,1.996],[1.07,0.489],[3.851,1.648],[0.943,0.314],[4.191,1.301],[0.708,0.158],[0.582,0.117],[-15.909,-12.322],[-17.171,3.974]],"v":[[-42.071,-15.532],[-41.324,-14.701],[-31.913,-5.305],[-29.515,-3.17],[-19.744,4.729],[-16.771,6.867],[-6.512,13.511],[-3.264,15.348],[7.639,20.899],[10.855,22.285],[22.593,26.788],[25.431,27.67],[38.179,31.084],[40.326,31.502],[42.071,31.786],[4.022,-31.786]],"c":true},"ix":2},"nm":"Path 2","mn":"ADBE Vector Shape - Group","hd":false},{"ty":"gf","o":{"a":0,"k":100,"ix":10},"r":1,"bm":0,"g":{"p":3,"k":{"a":0,"k":[0,0.631,0.776,1,0.5,0.386,0.624,0.994,1,0.141,0.471,0.988],"ix":9}},"s":{"a":0,"k":[70.5,33.625],"ix":5},"e":{"a":0,"k":[70.5,-269.875],"ix":6},"t":1,"nm":"Gradient Fill 1","mn":"ADBE Vector Graphic - G-Fill","hd":false},{"ty":"tr","p":{"a":0,"k":[182.347,378.48],"ix":2},"a":{"a":0,"k":[0,0],"ix":1},"s":{"a":0,"k":[100,100],"ix":3},"r":{"a":0,"k":0,"ix":6},"o":{"a":0,"k":100,"ix":7},"sk":{"a":0,"k":0,"ix":4},"sa":{"a":0,"k":0,"ix":5},"nm":"Transform"}],"nm":"Group 8","np":2,"cix":2,"bm":0,"ix":8,"mn":"ADBE Vector Group","hd":false},{"ty":"gr","it":[{"ind":0,"ty":"sh","ix":1,"ks":{"a":0,"k":{"i":[[-8.91,-29.019],[-13.202,6.835],[1.548,1.577],[0.432,0.436],[6.486,4.66],[0.221,0.15],[3.538,2.102],[0,0],[6.798,2.794],[4.276,1.332],[0.661,0.191],[4.176,0.863],[0.771,0.15]],"o":[[17.201,-3.95],[-1.502,-1.646],[-0.447,-0.448],[-5.675,-5.623],[-0.212,-0.16],[-3.355,-2.38],[0,0],[-6.323,-3.75],[-4.167,-1.727],[-0.671,-0.206],[-4.095,-1.21],[-0.779,-0.157],[16.006,12.306]],"v":[[-3.847,31.883],[42.097,15.566],[37.592,10.67],[36.278,9.352],[18.008,-6.096],[17.362,-6.563],[7.056,-13.291],[7.008,-13.339],[-12.7,-23.169],[-25.382,-27.717],[-27.356,-28.325],[-39.761,-31.436],[-42.097,-31.883]],"c":true},"ix":2},"nm":"Path 2","mn":"ADBE Vector Shape - Group","hd":false},{"ty":"gf","o":{"a":0,"k":100,"ix":10},"r":1,"bm":0,"g":{"p":3,"k":{"a":0,"k":[0,0.631,0.776,1,0.5,0.386,0.624,0.994,1,0.141,0.471,0.988],"ix":9}},"s":{"a":0,"k":[-71,266.875],"ix":5},"e":{"a":0,"k":[-71.5,-34.875],"ix":6},"t":1,"nm":"Gradient Fill 1","mn":"ADBE Vector Graphic - G-Fill","hd":false},{"ty":"tr","p":{"a":0,"k":[323.505,142.421],"ix":2},"a":{"a":0,"k":[0,0],"ix":1},"s":{"a":0,"k":[100,100],"ix":3},"r":{"a":0,"k":0,"ix":6},"o":{"a":0,"k":100,"ix":7},"sk":{"a":0,"k":0,"ix":4},"sa":{"a":0,"k":0,"ix":5},"nm":"Transform"}],"nm":"Group 9","np":2,"cix":2,"bm":0,"ix":9,"mn":"ADBE Vector Group","hd":false},{"ty":"gr","it":[{"ind":0,"ty":"sh","ix":1,"ks":{"a":0,"k":{"i":[[0,0],[5.959,-22.049],[-14.01,-7.489],[-0.86,33.77]],"o":[[-0.306,27.267],[18.364,4.281],[21.292,-26.181],[0,0]],"v":[[-31.87,-46.239],[-41.585,28.462],[7.416,46.239],[41.585,-46.239]],"c":true},"ix":2},"nm":"Path 2","mn":"ADBE Vector Shape - Group","hd":false},{"ty":"gf","o":{"a":0,"k":100,"ix":10},"r":1,"bm":0,"g":{"p":3,"k":{"a":0,"k":[0,0.631,0.776,1,0.5,0.386,0.624,0.994,1,0.141,0.471,0.988],"ix":9}},"s":{"a":0,"k":[-110.5,102.125],"ix":5},"e":{"a":0,"k":[-110.938,-202.625],"ix":6},"t":1,"nm":"Gradient Fill 1","mn":"ADBE Vector Graphic - G-Fill","hd":false},{"ty":"tr","p":{"a":0,"k":[363.472,310.637],"ix":2},"a":{"a":0,"k":[0,0],"ix":1},"s":{"a":0,"k":[100,100],"ix":3},"r":{"a":0,"k":0,"ix":6},"o":{"a":0,"k":100,"ix":7},"sk":{"a":0,"k":0,"ix":4},"sa":{"a":0,"k":0,"ix":5},"nm":"Transform"}],"nm":"Group 10","np":2,"cix":2,"bm":0,"ix":10,"mn":"ADBE Vector Group","hd":false},{"ty":"gr","it":[{"ind":0,"ty":"sh","ix":1,"ks":{"a":0,"k":{"i":[[12.006,-38.794],[-19.137,-0.235],[0,0]],"o":[[17.222,3.414],[0,0],[-22.901,2.767]],"v":[[-27.47,31.077],[27.471,36.625],[27.471,-36.626]],"c":true},"ix":2},"nm":"Path 2","mn":"ADBE Vector Shape - Group","hd":false},{"ty":"gf","o":{"a":0,"k":100,"ix":10},"r":1,"bm":0,"g":{"p":3,"k":{"a":0,"k":[0,0.631,0.776,1,0.5,0.386,0.624,0.994,1,0.141,0.471,0.988],"ix":9}},"s":{"a":0,"k":[31.313,268],"ix":5},"e":{"a":0,"k":[31.375,-36.625],"ix":6},"t":1,"nm":"Gradient Fill 1","mn":"ADBE Vector Graphic - G-Fill","hd":false},{"ty":"tr","p":{"a":0,"k":[221.56,144.87],"ix":2},"a":{"a":0,"k":[0,0],"ix":1},"s":{"a":0,"k":[100,100],"ix":3},"r":{"a":0,"k":0,"ix":6},"o":{"a":0,"k":100,"ix":7},"sk":{"a":0,"k":0,"ix":4},"sa":{"a":0,"k":0,"ix":5},"nm":"Transform"}],"nm":"Group 11","np":2,"cix":2,"bm":0,"ix":11,"mn":"ADBE Vector Group","hd":false},{"ty":"gr","it":[{"ind":0,"ty":"sh","ix":1,"ks":{"a":0,"k":{"i":[[18.39,-4.274],[-0.315,-27.245],[0,0],[21.276,26.154]],"o":[[5.961,22.042],[0,0],[-0.878,-33.739],[-13.977,7.467]],"v":[[-41.587,-28.462],[-31.869,46.193],[41.588,46.193],[7.416,-46.193]],"c":true},"ix":2},"nm":"Path 2","mn":"ADBE Vector Shape - Group","hd":false},{"ty":"gf","o":{"a":0,"k":100,"ix":10},"r":1,"bm":0,"g":{"p":3,"k":{"a":0,"k":[0,0.631,0.776,1,0.5,0.386,0.624,0.994,1,0.141,0.471,0.988],"ix":9}},"s":{"a":0,"k":[-111,200.875],"ix":5},"e":{"a":0,"k":[-111.5,-101.875],"ix":6},"t":1,"nm":"Gradient Fill 1","mn":"ADBE Vector Graphic - G-Fill","hd":false},{"ty":"tr","p":{"a":0,"k":[363.469,210.324],"ix":2},"a":{"a":0,"k":[0,0],"ix":1},"s":{"a":0,"k":[100,100],"ix":3},"r":{"a":0,"k":0,"ix":6},"o":{"a":0,"k":100,"ix":7},"sk":{"a":0,"k":0,"ix":4},"sa":{"a":0,"k":0,"ix":5},"nm":"Transform"}],"nm":"Group 12","np":2,"cix":2,"bm":0,"ix":12,"mn":"ADBE Vector Group","hd":false},{"ty":"gr","it":[{"ind":0,"ty":"sh","ix":1,"ks":{"a":0,"k":{"i":[[0,0],[0,0],[-17.994,-3.626],[-0.32,26.604]],"o":[[0,0],[19.865,0.223],[5.874,-21.561],[0,0]],"v":[[-33.425,-36.523],[-33.425,30.619],[23.753,36.523],[33.425,-36.523]],"c":true},"ix":2},"nm":"Path 2","mn":"ADBE Vector Shape - Group","hd":false},{"ty":"gf","o":{"a":0,"k":100,"ix":10},"r":1,"bm":0,"g":{"p":3,"k":{"a":0,"k":[0,0.631,0.776,1,0.5,0.386,0.624,0.994,1,0.141,0.471,0.988],"ix":9}},"s":{"a":0,"k":[-38,109.875],"ix":5},"e":{"a":0,"k":[-37.5,-191.875],"ix":6},"t":1,"nm":"Gradient Fill 1","mn":"ADBE Vector Graphic - G-Fill","hd":false},{"ty":"tr","p":{"a":0,"k":[290.316,300.921],"ix":2},"a":{"a":0,"k":[0,0],"ix":1},"s":{"a":0,"k":[100,100],"ix":3},"r":{"a":0,"k":0,"ix":6},"o":{"a":0,"k":100,"ix":7},"sk":{"a":0,"k":0,"ix":4},"sa":{"a":0,"k":0,"ix":5},"nm":"Transform"}],"nm":"Group 13","np":2,"cix":2,"bm":0,"ix":13,"mn":"ADBE Vector Group","hd":false},{"ty":"gr","it":[{"ind":0,"ty":"sh","ix":1,"ks":{"a":0,"k":{"i":[[0,0],[-17.266,3.422],[22.917,2.72]],"o":[[19.168,-0.224],[-12.024,-38.81],[0,0]],"v":[[-27.51,36.626],[27.51,31.044],[-27.51,-36.627]],"c":true},"ix":2},"nm":"Path 2","mn":"ADBE Vector Shape - Group","hd":false},{"ty":"gf","o":{"a":0,"k":100,"ix":10},"r":1,"bm":0,"g":{"p":3,"k":{"a":0,"k":[0,0.631,0.776,1,0.5,0.386,0.624,0.994,1,0.141,0.471,0.988],"ix":9}},"s":{"a":0,"k":[-31.375,267.75],"ix":5},"e":{"a":0,"k":[-31.5,-36.813],"ix":6},"t":1,"nm":"Gradient Fill 1","mn":"ADBE Vector Graphic - G-Fill","hd":false},{"ty":"tr","p":{"a":0,"k":[284.401,144.871],"ix":2},"a":{"a":0,"k":[0,0],"ix":1},"s":{"a":0,"k":[100,100],"ix":3},"r":{"a":0,"k":0,"ix":6},"o":{"a":0,"k":100,"ix":7},"sk":{"a":0,"k":0,"ix":4},"sa":{"a":0,"k":0,"ix":5},"nm":"Transform"}],"nm":"Group 14","np":2,"cix":2,"bm":0,"ix":14,"mn":"ADBE Vector Group","hd":false},{"ty":"gr","it":[{"ind":0,"ty":"sh","ix":1,"ks":{"a":0,"k":{"i":[[19.883,-0.232],[0,0],[0,0],[5.876,21.552]],"o":[[0,0],[0,0],[-0.321,-26.582],[-17.965,3.61]],"v":[[-33.42,-30.629],[-33.42,36.503],[33.42,36.503],[23.743,-36.503]],"c":true},"ix":2},"nm":"Path 1","mn":"ADBE Vector Shape - Group","hd":false},{"ty":"gf","o":{"a":0,"k":100,"ix":10},"r":1,"bm":0,"g":{"p":3,"k":{"a":0,"k":[0,0.631,0.776,1,0.5,0.386,0.624,0.994,1,0.141,0.471,0.988],"ix":9}},"s":{"a":0,"k":[-37,190.875],"ix":5},"e":{"a":0,"k":[-38.5,-110.875],"ix":6},"t":1,"nm":"Gradient Fill 1","mn":"ADBE Vector Graphic - G-Fill","hd":false},{"ty":"tr","p":{"a":0,"k":[290.316,220.009],"ix":2},"a":{"a":0,"k":[0,0],"ix":1},"s":{"a":0,"k":[100,100],"ix":3},"r":{"a":0,"k":0,"ix":6},"o":{"a":0,"k":100,"ix":7},"sk":{"a":0,"k":0,"ix":4},"sa":{"a":0,"k":0,"ix":5},"nm":"Transform"}],"nm":"Group 15","np":2,"cix":2,"bm":0,"ix":15,"mn":"ADBE Vector Group","hd":false},{"ty":"gr","it":[{"ind":0,"ty":"sh","ix":1,"ks":{"a":0,"k":{"i":[[0,0],[-12.029,38.81],[19.143,0.219]],"o":[[22.941,-2.705],[-17.28,-3.445],[0,0]],"v":[[-27.521,36.622],[27.521,-31.04],[-27.521,-36.622]],"c":true},"ix":2},"nm":"Path 2","mn":"ADBE Vector Shape - Group","hd":false},{"ty":"gf","o":{"a":0,"k":100,"ix":10},"r":1,"bm":0,"g":{"p":3,"k":{"a":0,"k":[0,0.631,0.776,1,0.5,0.386,0.624,0.994,1,0.141,0.471,0.988],"ix":9}},"s":{"a":0,"k":[-32.25,35.875],"ix":5},"e":{"a":0,"k":[-31.625,-267.875],"ix":6},"t":1,"nm":"Gradient Fill 1","mn":"ADBE Vector Graphic - G-Fill","hd":false},{"ty":"tr","p":{"a":0,"k":[284.411,376.043],"ix":2},"a":{"a":0,"k":[0,0],"ix":1},"s":{"a":0,"k":[100,100],"ix":3},"r":{"a":0,"k":0,"ix":6},"o":{"a":0,"k":100,"ix":7},"sk":{"a":0,"k":0,"ix":4},"sa":{"a":0,"k":0,"ix":5},"nm":"Transform"}],"nm":"Group 16","np":2,"cix":2,"bm":0,"ix":16,"mn":"ADBE Vector Group","hd":false}],"ip":0,"op":180,"st":0,"bm":0}],"markers":[]}